{"nodes": [{"id": "users_minster_code_go_ruyi_apps_lina_core_api_plugin_v1_plugin_go", "label": "plugin.go", "file_type": "code", "source_file": "apps/lina-core/api/plugin/v1/plugin.go", "source_location": "L1"}, {"id": "v1_plugintype", "label": "PluginType", "file_type": "code", "source_file": "apps/lina-core/api/plugin/v1/plugin.go", "source_location": "L4"}, {"id": "v1_plugintype_string", "label": ".String()", "file_type": "code", "source_file": "apps/lina-core/api/plugin/v1/plugin.go", "source_location": "L13"}, {"id": "v1_plugindistribution", "label": "PluginDistribution", "file_type": "code", "source_file": "apps/lina-core/api/plugin/v1/plugin.go", "source_location": "L16"}, {"id": "v1_plugindistribution_string", "label": ".String()", "file_type": "code", "source_file": "apps/lina-core/api/plugin/v1/plugin.go", "source_location": "L25"}, {"id": "v1_runtimestate", "label": "RuntimeState", "file_type": "code", "source_file": "apps/lina-core/api/plugin/v1/plugin.go", "source_location": "L28"}, {"id": "v1_runtimestate_string", "label": ".String()", "file_type": "code", "source_file": "apps/lina-core/api/plugin/v1/plugin.go", "source_location": "L40"}, {"id": "v1_runtimeabnormalreason", "label": "RuntimeAbnormalReason", "file_type": "code", "source_file": "apps/lina-core/api/plugin/v1/plugin.go", "source_location": "L43"}, {"id": "v1_runtimeabnormalreason_string", "label": ".String()", "file_type": "code", "source_file": "apps/lina-core/api/plugin/v1/plugin.go", "source_location": "L52"}, {"id": "v1_runtimefailurephase", "label": "RuntimeFailurePhase", "file_type": "code", "source_file": "apps/lina-core/api/plugin/v1/plugin.go", "source_location": "L55"}, {"id": "v1_runtimefailurephase_string", "label": ".String()", "file_type": "code", "source_file": "apps/lina-core/api/plugin/v1/plugin.go", "source_location": "L69"}, {"id": "v1_scopenature", "label": "ScopeNature", "file_type": "code", "source_file": "apps/lina-core/api/plugin/v1/plugin.go", "source_location": "L72"}, {"id": "v1_scopenature_string", "label": ".String()", "file_type": "code", "source_file": "apps/lina-core/api/plugin/v1/plugin.go", "source_location": "L81"}, {"id": "v1_installmode", "label": "InstallMode", "file_type": "code", "source_file": "apps/lina-core/api/plugin/v1/plugin.go", "source_location": "L84"}, {"id": "v1_installmode_string", "label": ".String()", "file_type": "code", "source_file": "apps/lina-core/api/plugin/v1/plugin.go", "source_location": "L93"}, {"id": "v1_authorizationstatus", "label": "AuthorizationStatus", "file_type": "code", "source_file": "apps/lina-core/api/plugin/v1/plugin.go", "source_location": "L96"}, {"id": "v1_authorizationstatus_string", "label": ".String()", "file_type": "code", "source_file": "apps/lina-core/api/plugin/v1/plugin.go", "source_location": "L106"}, {"id": "v1_dependencystatus", "label": "DependencyStatus", "file_type": "code", "source_file": "apps/lina-core/api/plugin/v1/plugin.go", "source_location": "L109"}, {"id": "v1_dependencystatus_string", "label": ".String()", "file_type": "code", "source_file": "apps/lina-core/api/plugin/v1/plugin.go", "source_location": "L120"}, {"id": "v1_frameworkstatus", "label": "FrameworkStatus", "file_type": "code", "source_file": "apps/lina-core/api/plugin/v1/plugin.go", "source_location": "L123"}, {"id": "v1_frameworkstatus_string", "label": ".String()", "file_type": "code", "source_file": "apps/lina-core/api/plugin/v1/plugin.go", "source_location": "L133"}, {"id": "v1_blockercode", "label": "BlockerCode", "file_type": "code", "source_file": "apps/lina-core/api/plugin/v1/plugin.go", "source_location": "L136"}, {"id": "v1_blockercode_string", "label": ".String()", "file_type": "code", "source_file": "apps/lina-core/api/plugin/v1/plugin.go", "source_location": "L152"}], "edges": [{"source": "users_minster_code_go_ruyi_apps_lina_core_api_plugin_v1_plugin_go", "target": "v1_plugintype", "relation": "contains", "confidence": "EXTRACTED", "source_file": "apps/lina-core/api/plugin/v1/plugin.go", "source_location": "L4", "weight": 1.0}, {"source": "v1_plugintype", "target": "v1_plugintype_string", "relation": "method", "confidence": "EXTRACTED", "source_file": "apps/lina-core/api/plugin/v1/plugin.go", "source_location": "L13", "weight": 1.0}, {"source": "users_minster_code_go_ruyi_apps_lina_core_api_plugin_v1_plugin_go", "target": "v1_plugindistribution", "relation": "contains", "confidence": "EXTRACTED", "source_file": "apps/lina-core/api/plugin/v1/plugin.go", "source_location": "L16", "weight": 1.0}, {"source": "v1_plugindistribution", "target": "v1_plugindistribution_string", "relation": "method", "confidence": "EXTRACTED", "source_file": "apps/lina-core/api/plugin/v1/plugin.go", "source_location": "L25", "weight": 1.0}, {"source": "users_minster_code_go_ruyi_apps_lina_core_api_plugin_v1_plugin_go", "target": "v1_runtimestate", "relation": "contains", "confidence": "EXTRACTED", "source_file": "apps/lina-core/api/plugin/v1/plugin.go", "source_location": "L28", "weight": 1.0}, {"source": "v1_runtimestate", "target": "v1_runtimestate_string", "relation": "method", "confidence": "EXTRACTED", "source_file": "apps/lina-core/api/plugin/v1/plugin.go", "source_location": "L40", "weight": 1.0}, {"source": "users_minster_code_go_ruyi_apps_lina_core_api_plugin_v1_plugin_go", "target": "v1_runtimeabnormalreason", "relation": "contains", "confidence": "EXTRACTED", "source_file": "apps/lina-core/api/plugin/v1/plugin.go", "source_location": "L43", "weight": 1.0}, {"source": "v1_runtimeabnormalreason", "target": "v1_runtimeabnormalreason_string", "relation": "method", "confidence": "EXTRACTED", "source_file": "apps/lina-core/api/plugin/v1/plugin.go", "source_location": "L52", "weight": 1.0}, {"source": "users_minster_code_go_ruyi_apps_lina_core_api_plugin_v1_plugin_go", "target": "v1_runtimefailurephase", "relation": "contains", "confidence": "EXTRACTED", "source_file": "apps/lina-core/api/plugin/v1/plugin.go", "source_location": "L55", "weight": 1.0}, {"source": "v1_runtimefailurephase", "target": "v1_runtimefailurephase_string", "relation": "method", "confidence": "EXTRACTED", "source_file": "apps/lina-core/api/plugin/v1/plugin.go", "source_location": "L69", "weight": 1.0}, {"source": "users_minster_code_go_ruyi_apps_lina_core_api_plugin_v1_plugin_go", "target": "v1_scopenature", "relation": "contains", "confidence": "EXTRACTED", "source_file": "apps/lina-core/api/plugin/v1/plugin.go", "source_location": "L72", "weight": 1.0}, {"source": "v1_scopenature", "target": "v1_scopenature_string", "relation": "method", "confidence": "EXTRACTED", "source_file": "apps/lina-core/api/plugin/v1/plugin.go", "source_location": "L81", "weight": 1.0}, {"source": "users_minster_code_go_ruyi_apps_lina_core_api_plugin_v1_plugin_go", "target": "v1_installmode", "relation": "contains", "confidence": "EXTRACTED", "source_file": "apps/lina-core/api/plugin/v1/plugin.go", "source_location": "L84", "weight": 1.0}, {"source": "v1_installmode", "target": "v1_installmode_string", "relation": "method", "confidence": "EXTRACTED", "source_file": "apps/lina-core/api/plugin/v1/plugin.go", "source_location": "L93", "weight": 1.0}, {"source": "users_minster_code_go_ruyi_apps_lina_core_api_plugin_v1_plugin_go", "target": "v1_authorizationstatus", "relation": "contains", "confidence": "EXTRACTED", "source_file": "apps/lina-core/api/plugin/v1/plugin.go", "source_location": "L96", "weight": 1.0}, {"source": "v1_authorizationstatus", "target": "v1_authorizationstatus_string", "relation": "method", "confidence": "EXTRACTED", "source_file": "apps/lina-core/api/plugin/v1/plugin.go", "source_location": "L106", "weight": 1.0}, {"source": "users_minster_code_go_ruyi_apps_lina_core_api_plugin_v1_plugin_go", "target": "v1_dependencystatus", "relation": "contains", "confidence": "EXTRACTED", "source_file": "apps/lina-core/api/plugin/v1/plugin.go", "source_location": "L109", "weight": 1.0}, {"source": "v1_dependencystatus", "target": "v1_dependencystatus_string", "relation": "method", "confidence": "EXTRACTED", "source_file": "apps/lina-core/api/plugin/v1/plugin.go", "source_location": "L120", "weight": 1.0}, {"source": "users_minster_code_go_ruyi_apps_lina_core_api_plugin_v1_plugin_go", "target": "v1_frameworkstatus", "relation": "contains", "confidence": "EXTRACTED", "source_file": "apps/lina-core/api/plugin/v1/plugin.go", "source_location": "L123", "weight": 1.0}, {"source": "v1_frameworkstatus", "target": "v1_frameworkstatus_string", "relation": "method", "confidence": "EXTRACTED", "source_file": "apps/lina-core/api/plugin/v1/plugin.go", "source_location": "L133", "weight": 1.0}, {"source": "users_minster_code_go_ruyi_apps_lina_core_api_plugin_v1_plugin_go", "target": "v1_blockercode", "relation": "contains", "confidence": "EXTRACTED", "source_file": "apps/lina-core/api/plugin/v1/plugin.go", "source_location": "L136", "weight": 1.0}, {"source": "v1_blockercode", "target": "v1_blockercode_string", "relation": "method", "confidence": "EXTRACTED", "source_file": "apps/lina-core/api/plugin/v1/plugin.go", "source_location": "L152", "weight": 1.0}], "raw_calls": [{"caller_nid": "v1_plugintype_string", "callee": "string", "is_member_call": false, "source_file": "apps/lina-core/api/plugin/v1/plugin.go", "source_location": "L13"}, {"caller_nid": "v1_plugindistribution_string", "callee": "string", "is_member_call": false, "source_file": "apps/lina-core/api/plugin/v1/plugin.go", "source_location": "L25"}, {"caller_nid": "v1_runtimestate_string", "callee": "string", "is_member_call": false, "source_file": "apps/lina-core/api/plugin/v1/plugin.go", "source_location": "L40"}, {"caller_nid": "v1_runtimeabnormalreason_string", "callee": "string", "is_member_call": false, "source_file": "apps/lina-core/api/plugin/v1/plugin.go", "source_location": "L52"}, {"caller_nid": "v1_runtimefailurephase_string", "callee": "string", "is_member_call": false, "source_file": "apps/lina-core/api/plugin/v1/plugin.go", "source_location": "L69"}, {"caller_nid": "v1_scopenature_string", "callee": "string", "is_member_call": false, "source_file": "apps/lina-core/api/plugin/v1/plugin.go", "source_location": "L81"}, {"caller_nid": "v1_installmode_string", "callee": "string", "is_member_call": false, "source_file": "apps/lina-core/api/plugin/v1/plugin.go", "source_location": "L93"}, {"caller_nid": "v1_authorizationstatus_string", "callee": "string", "is_member_call": false, "source_file": "apps/lina-core/api/plugin/v1/plugin.go", "source_location": "L106"}, {"caller_nid": "v1_dependencystatus_string", "callee": "string", "is_member_call": false, "source_file": "apps/lina-core/api/plugin/v1/plugin.go", "source_location": "L120"}, {"caller_nid": "v1_frameworkstatus_string", "callee": "string", "is_member_call": false, "source_file": "apps/lina-core/api/plugin/v1/plugin.go", "source_location": "L133"}, {"caller_nid": "v1_blockercode_string", "callee": "string", "is_member_call": false, "source_file": "apps/lina-core/api/plugin/v1/plugin.go", "source_location": "L152"}]}